<annotation>
	<folder>juice</folder>
	<filename>j25.jpg</filename>
	<path>/home/admin123/Desktop/Dataset/juice/j25.jpg</path>
	<source>
		<database>Unknown</database>
	</source>
	<size>
		<width>3280</width>
		<height>2464</height>
		<depth>3</depth>
	</size>
	<segmented>0</segmented>
	<object>
		<name>juice</name>
		<pose>Unspecified</pose>
		<truncated>0</truncated>
		<difficult>0</difficult>
		<bndbox>
			<xmin>1319</xmin>
			<ymin>1017</ymin>
			<xmax>1708</xmax>
			<ymax>2014</ymax>
		</bndbox>
	</object>
	<object>
		<name>juice</name>
		<pose>Unspecified</pose>
		<truncated>0</truncated>
		<difficult>0</difficult>
		<bndbox>
			<xmin>1661</xmin>
			<ymin>1085</ymin>
			<xmax>2203</xmax>
			<ymax>2219</ymax>
		</bndbox>
	</object>
	<object>
		<name>juice</name>
		<pose>Unspecified</pose>
		<truncated>0</truncated>
		<difficult>0</difficult>
		<bndbox>
			<xmin>1722</xmin>
			<ymin>1017</ymin>
			<xmax>1990</xmax>
			<ymax>1156</ymax>
		</bndbox>
	</object>
</annotation>
