<annotation>
	<folder>groups</folder>
	<filename>picg15.jpg</filename>
	<path>/home/admin123/Desktop/Dataset/groups/picg15.jpg</path>
	<source>
		<database>Unknown</database>
	</source>
	<size>
		<width>1280</width>
		<height>720</height>
		<depth>3</depth>
	</size>
	<segmented>0</segmented>
	<object>
		<name>yoghurt</name>
		<pose>Unspecified</pose>
		<truncated>0</truncated>
		<difficult>0</difficult>
		<bndbox>
			<xmin>55</xmin>
			<ymin>384</ymin>
			<xmax>188</xmax>
			<ymax>421</ymax>
		</bndbox>
	</object>
	<object>
		<name>yoghurt</name>
		<pose>Unspecified</pose>
		<truncated>0</truncated>
		<difficult>0</difficult>
		<bndbox>
			<xmin>49</xmin>
			<ymin>416</ymin>
			<xmax>223</xmax>
			<ymax>471</ymax>
		</bndbox>
	</object>
	<object>
		<name>yoghurt</name>
		<pose>Unspecified</pose>
		<truncated>0</truncated>
		<difficult>0</difficult>
		<bndbox>
			<xmin>45</xmin>
			<ymin>457</ymin>
			<xmax>245</xmax>
			<ymax>554</ymax>
		</bndbox>
	</object>
	<object>
		<name>yoghurt</name>
		<pose>Unspecified</pose>
		<truncated>0</truncated>
		<difficult>0</difficult>
		<bndbox>
			<xmin>59</xmin>
			<ymin>530</ymin>
			<xmax>350</xmax>
			<ymax>697</ymax>
		</bndbox>
	</object>
	<object>
		<name>caramel</name>
		<pose>Unspecified</pose>
		<truncated>0</truncated>
		<difficult>0</difficult>
		<bndbox>
			<xmin>195</xmin>
			<ymin>296</ymin>
			<xmax>338</xmax>
			<ymax>430</ymax>
		</bndbox>
	</object>
	<object>
		<name>caramel</name>
		<pose>Unspecified</pose>
		<truncated>0</truncated>
		<difficult>0</difficult>
		<bndbox>
			<xmin>330</xmin>
			<ymin>308</ymin>
			<xmax>378</xmax>
			<ymax>421</ymax>
		</bndbox>
	</object>
	<object>
		<name>caramel</name>
		<pose>Unspecified</pose>
		<truncated>0</truncated>
		<difficult>0</difficult>
		<bndbox>
			<xmin>212</xmin>
			<ymin>419</ymin>
			<xmax>349</xmax>
			<ymax>550</ymax>
		</bndbox>
	</object>
	<object>
		<name>juice</name>
		<pose>Unspecified</pose>
		<truncated>0</truncated>
		<difficult>0</difficult>
		<bndbox>
			<xmin>646</xmin>
			<ymin>295</ymin>
			<xmax>791</xmax>
			<ymax>696</ymax>
		</bndbox>
	</object>
	<object>
		<name>juice</name>
		<pose>Unspecified</pose>
		<truncated>1</truncated>
		<difficult>0</difficult>
		<bndbox>
			<xmin>451</xmin>
			<ymin>295</ymin>
			<xmax>663</xmax>
			<ymax>720</ymax>
		</bndbox>
	</object>
	<object>
		<name>juice</name>
		<pose>Unspecified</pose>
		<truncated>0</truncated>
		<difficult>0</difficult>
		<bndbox>
			<xmin>345</xmin>
			<ymin>260</ymin>
			<xmax>497</xmax>
			<ymax>692</ymax>
		</bndbox>
	</object>
	<object>
		<name>juice</name>
		<pose>Unspecified</pose>
		<truncated>0</truncated>
		<difficult>0</difficult>
		<bndbox>
			<xmin>503</xmin>
			<ymin>273</ymin>
			<xmax>624</xmax>
			<ymax>302</ymax>
		</bndbox>
	</object>
</annotation>
